{
	"salad": {
		"sizes": [
			{
				"name": "Junior",
				"price": 6.95,
				"hex": "474747"
			},
			{
				"name": "Regular",
				"price": 9.95,
				"hex": "474747"
			},
			{
				"name": "Large",
				"price": 13.95,
				"hex": "474747"
			},
			{
				"name": "Family",
				"price": 26.95,
				"hex": "474747"
			},
			{
				"name": "Party",
				"price": 49.95,
				"hex": "474747"
			}
		],
		"lettuce": [
			{
				"name": "Romaine",
				"description": "",
        "hex": ""
			},
			{
				"name": "Arugala",
				"description": "",
        "hex": ""
			},
			{
				"name": "Baby Kale",
				"description": "",
        "hex": ""
			},
			{
				"name": "Baby Spinach",
				"description": "",
        "hex": ""
			},
			{
				"name": "Iceberg",
				"description": "",
        "hex": ""
			},
			{
				"name": "Mesculine",
				"description": "",
        "hex": ""
			}
		],
		"vegetables": [
			{
				"name": "Avocado",
				"description": "",
        "hex": ""
			},
			{
				"name": "Beets",
				"description": "",
        "hex": ""
			},
			{
				"name": "Butternut Squash (Roasted)",
				"description": "",
				"hex": ""
			},
			{
				"name": "Celery",
				"description": "",
				"hex": ""
      },
			{
				"name": "Chick Peas",
				"description": "",
				"hex": ""
			},
			{
				"name": "Corn (Baby)",
				"description": "",
				"hex": ""
			},
			{
				"name": "Corn (Canned)",
				"description": "",
				"hex": ""
			},
			{
				"name": "Corn (Fresh)",
				"description": "",
				"hex": ""
			},
			{
				"name": "Cucumber",
				"description": "",
				"hex": ""
			},
			{
				"name": "Egg (Hard Boiled)",
				"description": "",
				"hex": ""
			},
			{
				"name": "Eggplant (Roasted)",
				"description": "",
				"hex": ""
			},
			{
				"name": "Egg Whites",
				"description": "",
				"hex": ""
			},
			{
				"name": "Hearts of Palm",
				"description": "",
				"hex": ""
			},
			{
				"name": "Jicama",
				"description": "",
				"hex": ""
			},
			{
				"name": "Mandarin Orange",
				"description": "",
				"hex": ""
			},
			{
				"name": "Mango",
				"description": "",
				"hex": ""
			},
			{
				"name": "Mushrooms",
				"description": "",
				"hex": ""
			},
			{
				"name": "Olives (Black)",
				"description": "",
				"hex": ""
			},
			{
				"name": "Olives (Green)",
				"description": "",
				"hex": ""
			},
			{
				"name": "Pepper (Green)",
				"description": "",
				"hex": ""
			},
			{
				"name": "Pepper (Red)",
				"description": "",
				"hex": ""
			},
			{
				"name": "Pepper (Red, Roasted)",
				"description": "",
				"hex": ""
			},
			{
				"name": "Pepper (Mixed Colors)",
				"description": "",
				"hex": ""
			},
			{
				"name": "Pickles",
				"description": "",
				"hex": ""
			},
			{
				"name": "Portobello Mushrooms (Roasted)",
				"description": "",
				"hex": ""
			},
			{
				"name": "Raddish",
				"description": "",
				"hex": ""
			},
			{
				"name": "Red Beans",
				"description": "",
				"hex": ""
			},
			{
				"name": "Red Onion",
				"description": "",
				"hex": ""
			},
			{
				"name": "Scallion",
				"description": "",
				"hex": ""
			},
			{
				"name": "Snow Peas",
				"description": "",
				"hex": ""
			},
			{
				"name": "Sprouts",
				"description": "",
				"hex": ""
			},
			{
				"name": "Strawberries",
				"description": "",
				"hex": "E3125C"
			},
			{
				"name": "String Beans",
				"description": "",
				"hex": ""
			},
			{
				"name": "Squash",
				"description": "",
				"hex": ""
			},
			{
				"name": "Sweet Potatoes (Roasted)",
				"description": "",
				"hex": ""
			},
			{
				"name": "Tomatoes (Cherry)",
				"description": "",
				"hex": ""
			},
			{
				"name": "Tomatoes (Regular)",
				"description": "",
				"hex": ""
			},
			{
				"name": "Tomatoes (Sun Dried)",
				"description": "",
				"hex": ""
			},
			{
				"name": "Water Chestnuts",
				"description": "",
				"hex": ""
			},
			{
				"name": "Yellow Squash (Roasted)",
				"description": "",
				"hex": ""
			},
			{
				"name": "Zucchini",
				"description": "",
				"hex": ""
			},
			{
				"name": "Zucchini (Roasted)",
				"description": "",
				"hex": ""
			}
		],
		"toppings": [
			{
				"name": "Almonds (Caramelized)",
				"description": "",
				"hex": ""
			},
			{
				"name": "Almonds (Plain)",
				"description": "",
				"hex": ""
			},
			{
				"name": "Almonds (Salted)",
				"description": "",
				"hex": ""
			},
			{
				"name": "Bacos",
				"description": "",
				"hex": ""
			},
			{
				"name": "Bagel Chips",
				"description": "",
				"hex": ""
			},
			{
				"name": "Barley",
				"description": "",
				"hex": ""
			},
			{
				"name": "Cantaloupe",
				"description": "",
				"hex": ""
			},
			{
				"name": "Cashews",
				"description": "",
				"hex": ""
			},
			{
				"name": "Chinese Noodles",
				"description": "",
				"hex": ""
			},
			{
				"name": "Couscous",
				"description": "",
				"hex": ""
			},
			{
				"name": "Craisins",
				"description": "",
				"hex": ""
			},
			{
				"name": "Croutons",
				"description": "",
				"hex": ""
			},
			{
				"name": "Dried Blueberries",
				"description": "",
				"hex": ""
			},
			{
				"name": "Farro",
				"description": "",
				"hex": ""
			},
			{
				"name": "Granola",
				"description": "",
				"hex": ""
			},
			{
				"name": "Jalapenõ Peppers",
				"description": "",
				"hex": ""
			},
			{
				"name": "Orzo",
				"description": "",
				"hex": ""
			},
			{
				"name": "Pear",
				"description": "",
				"hex": ""
			},
			{
				"name": "Pecan Nuts",
				"description": "",
				"hex": ""
			},
			{
				"name": "Pine Nuts",
				"description": "",
				"hex": ""
			},
			{
				"name": "Pistachios",
				"description": "",
				"hex": ""
			},
			{
				"name": "Pomegranate",
				"description": "",
				"hex": ""
			},
			{
				"name": "Quinoa",
				"description": "",
				"hex": ""
			},
			{
				"name": "Raisins",
				"description": "",
				"hex": ""
			},
			{
				"name": "Sesame",
				"description": "",
				"hex": ""
			},
			{
				"name": "Sun Flower Seeds",
				"description": "",
				"hex": ""
			},
			{
				"name": "Terra Chips",
				"description": "",
				"hex": ""
			},
			{
				"name": "Tortilla Chips",
				"description": "",
				"hex": ""
			},
			{
				"name": "Walnuts",
				"description": "",
				"hex": ""
			},
			{
				"name": "Whear Berry",
				"description": "",
				"hex": ""
			}
		],
		"dressings": [
			{
				"name": "Balsamic Vinaigrette",
				"description": "",
				"hex": ""
			},
			{
				"name": "Balsamic Vinegar",
				"description": "",
				"hex": ""
			},
			{
				"name": "Basil Vinaigrette",
				"description": "",
				"hex": ""
			},
			{
				"name": "Buttermilk Ranch",
				"description": "",
				"hex": ""
			},
			{
				"name": "Caesar (Classic)",
				"description": "",
				"hex": ""
			},
			{
				"name": "Caesar (Light)",
				"description": "",
				"hex": ""
			},
			{
				"name": "Carrot Ginger",
				"description": "",
				"hex": ""
			},
			{
				"name": "Cucumber Wasabi",
				"description": "",
				"hex": ""
			},
			{
				"name": "Dill",
				"description": "",
				"hex": ""
			},
			{
				"name": "Lemon Juice",
				"description": "",
				"hex": ""
			},
			{
				"name": "French",
				"description": "",
				"hex": ""
			},
			{
				"name": "French (Light)",
				"description": "",
				"hex": ""
			},
			{
				"name": "Greek",
				"description": "",
				"hex": ""
			},
			{
				"name": "Honey Dijon",
				"description": "",
				"hex": ""
			},
			{
				"name": "Honey Mustard",
				"description": "",
				"hex": ""
			},
			{
				"name": "Hot Sauce",
				"description": "",
				"hex": ""
			},
			{
				"name": "Italian",
				"description": "",
				"hex": ""
			},
			{
				"name": "Italian (Creamy)",
				"description": "",
				"hex": ""
			},
			{
				"name": "Italian (Light)",
				"description": "",
				"hex": ""
			},
			{
				"name": "Olive Oil",
				"description": "",
				"hex": ""
			},
			{
				"name": "Raspberry Walnut Vinaigrette",
				"description": "",
				"hex": ""
			},
			{
				"name": "Red Wine Vinaigrette",
				"description": "",
				"hex": ""
			},
			{
				"name": "Russian",
				"description": "",
				"hex": ""
			},
			{
				"name": "Tehini",
				"description": "",
				"hex": ""
			},
			{
				"name": "Teriyaki Vinaigrette",
				"description": "",
				"hex": ""
			},
			{
				"name": "Thousand Island",
				"description": "",
				"hex": ""
			}
		]
	}
}
